LICENSE
README.md
setup.py
sar_handler/__init__.py
sar_handler/assistive_funcs.py
sar_handler/check_validity_of_values.py
sar_handler/csv_dataloader.py
sar_handler/dataset_creator.py
sar_handler/fastaniso.py
sar_handler/image_processing.py
sar_handler.egg-info/PKG-INFO
sar_handler.egg-info/SOURCES.txt
sar_handler.egg-info/dependency_links.txt
sar_handler.egg-info/requires.txt
sar_handler.egg-info/top_level.txt