Metadata-Version: 2.1
Name: sar-handler
Version: 0.1.8
Summary: Handler SAR images
Home-page: https://github.com/Felecort/SAR_Handler
Author: Felecort
License: MIT
Platform: UNKNOWN
License-File: LICENSE
